personalitygen-0.1.3.dist-info/METADATA
personalitygen-0.1.3.dist-info/WHEEL
personalitygen-0.1.3.dist-info/entry_points.txt
personalitygen-0.1.3.dist-info/licenses/LICENSE
personalitygen/__init__.py
personalitygen/constants.py
personalitygen/enums.py
personalitygen/personality.py
personalitygen/py.typed
personalitygen/randomness.py
personalitygen/traits.py
personalitygen-0.1.3.dist-info/RECORD
