Metadata-Version: 2.1
Name: personalitygen
Version: 0.1.3
Summary: Generate and manage simulated human-like personalities based on the Big Five model.
Keywords: personality,big-five,ocean,simulation
Author-Email: "B.T. Franklin" <brandon.franklin@gmail.com>
License: MIT License
Classifier: Programming Language :: Python :: 3
Classifier: Programming Language :: Python :: 3 :: Only
Classifier: Programming Language :: Python :: 3.11
Classifier: Programming Language :: Python :: 3.12
Classifier: Programming Language :: Python :: 3.13
Classifier: Programming Language :: Python :: 3.14
Classifier: Typing :: Typed
Classifier: License :: OSI Approved :: MIT License
Classifier: Operating System :: OS Independent
Classifier: Intended Audience :: Developers
Classifier: Topic :: Software Development :: Libraries :: Python Modules
Classifier: Topic :: Utilities
Project-URL: Homepage, https://github.com/btfranklin/personalitygen
Project-URL: Issues, https://github.com/btfranklin/personalitygen/issues
Project-URL: Changelog, https://github.com/btfranklin/personalitygen/releases
Project-URL: Repository, https://github.com/btfranklin/personalitygen.git
Requires-Python: >=3.11
